infinite_training/__init__.py
infinite_training-1.0.0.dist-info/LICENSE
infinite_training-1.0.0.dist-info/METADATA
infinite_training-1.0.0.dist-info/WHEEL
infinite_training-1.0.0.dist-info/top_level.txt
infinite_training-1.0.0.dist-info/RECORD
