Metadata-Version: 2.1
Name: infinite-training
Version: 1.0.0
Summary: The python package for training ML models base on loss, metrics and timeout.
Author-email: Nguyễn Chí Vỹ <vyncint@icloud.com>
Project-URL: Homepage, https://github.com/vyncint/infinite-training
Project-URL: Bug Tracker, https://github.com/vyncint/infinite-training/issues
Classifier: Programming Language :: Python :: 3
Classifier: License :: OSI Approved :: MIT License
Classifier: Operating System :: OS Independent
Requires-Python: >=3.7
License-File: LICENSE
